website_scraper/__init__.py
website_scraper/cli.py
website_scraper/intelligent_scraper.py
website_scraper/scraper.py
website_scraper/browser/__init__.py
website_scraper/browser/playwright_driver.py
website_scraper/browser/stealth.py
website_scraper/exporters/__init__.py
website_scraper/exporters/base.py
website_scraper/exporters/csv_exporter.py
website_scraper/exporters/factory.py
website_scraper/exporters/json_exporter.py
website_scraper/exporters/markdown_exporter.py
website_scraper/extractors/__init__.py
website_scraper/extractors/content.py
website_scraper/extractors/links.py
website_scraper/llm/__init__.py
website_scraper/llm/anthropic_provider.py
website_scraper/llm/base.py
website_scraper/llm/factory.py
website_scraper/llm/gemini_provider.py
website_scraper/llm/ollama_provider.py
website_scraper/llm/openai_provider.py
website_scraper-0.2.0.dist-info/METADATA
website_scraper-0.2.0.dist-info/WHEEL
website_scraper-0.2.0.dist-info/entry_points.txt
website_scraper-0.2.0.dist-info/licenses/LICENSE
website_scraper-0.2.0.dist-info/RECORD
