Metadata-Version: 2.4
Name: website-scraper
Version: 0.2.0
Summary: Intelligent web scraper with Playwright browser automation, optional LLM-powered content extraction, and Cloudflare bypass
Project-URL: Homepage, https://github.com/ml-lubich/website-scraper
Project-URL: Documentation, https://github.com/ml-lubich/website-scraper#readme
Project-URL: Repository, https://github.com/ml-lubich/website-scraper.git
Project-URL: Issues, https://github.com/ml-lubich/website-scraper/issues
Project-URL: Changelog, https://github.com/ml-lubich/website-scraper/blob/main/CHANGELOG.md
Author-email: Misha Lubich <michaelle.lubich@gmail.com>
Maintainer-email: Misha Lubich <michaelle.lubich@gmail.com>
License: MIT
License-File: LICENSE
Keywords: ai,browser-automation,cloudflare-bypass,content-extraction,crawler,llm,playwright,scraping,stealth,web-scraper
Classifier: Development Status :: 4 - Beta
Classifier: Intended Audience :: Developers
Classifier: License :: OSI Approved :: MIT License
Classifier: Operating System :: OS Independent
Classifier: Programming Language :: Python :: 3
Classifier: Programming Language :: Python :: 3.9
Classifier: Programming Language :: Python :: 3.10
Classifier: Programming Language :: Python :: 3.11
Classifier: Programming Language :: Python :: 3.12
Classifier: Topic :: Internet :: WWW/HTTP :: Indexing/Search
Classifier: Topic :: Software Development :: Libraries :: Python Modules
Classifier: Typing :: Typed
Requires-Python: >=3.9
Requires-Dist: aiofiles>=23.0.0
Requires-Dist: aiohttp>=3.9.0
Requires-Dist: beautifulsoup4>=4.12.0
Requires-Dist: fake-useragent>=1.4.0
Requires-Dist: lxml>=4.9.0
Requires-Dist: playwright>=1.40.0
Requires-Dist: requests>=2.31.0
Requires-Dist: tqdm>=4.66.0
Provides-Extra: all
Requires-Dist: anthropic>=0.18.0; extra == 'all'
Requires-Dist: black>=23.0.0; extra == 'all'
Requires-Dist: build>=1.0.0; extra == 'all'
Requires-Dist: google-generativeai>=0.4.0; extra == 'all'
Requires-Dist: mypy>=1.0.0; extra == 'all'
Requires-Dist: openai>=1.0.0; extra == 'all'
Requires-Dist: pytest-asyncio>=0.21.0; extra == 'all'
Requires-Dist: pytest-cov>=4.0.0; extra == 'all'
Requires-Dist: pytest-mock>=3.12.0; extra == 'all'
Requires-Dist: pytest>=7.0.0; extra == 'all'
Requires-Dist: ruff>=0.1.0; extra == 'all'
Requires-Dist: twine>=4.0.0; extra == 'all'
Provides-Extra: all-llm
Requires-Dist: anthropic>=0.18.0; extra == 'all-llm'
Requires-Dist: google-generativeai>=0.4.0; extra == 'all-llm'
Requires-Dist: openai>=1.0.0; extra == 'all-llm'
Provides-Extra: anthropic
Requires-Dist: anthropic>=0.18.0; extra == 'anthropic'
Provides-Extra: dev
Requires-Dist: black>=23.0.0; extra == 'dev'
Requires-Dist: build>=1.0.0; extra == 'dev'
Requires-Dist: mypy>=1.0.0; extra == 'dev'
Requires-Dist: pytest-asyncio>=0.21.0; extra == 'dev'
Requires-Dist: pytest-cov>=4.0.0; extra == 'dev'
Requires-Dist: pytest-mock>=3.12.0; extra == 'dev'
Requires-Dist: pytest>=7.0.0; extra == 'dev'
Requires-Dist: ruff>=0.1.0; extra == 'dev'
Requires-Dist: twine>=4.0.0; extra == 'dev'
Provides-Extra: gemini
Requires-Dist: google-generativeai>=0.4.0; extra == 'gemini'
Provides-Extra: llm
Requires-Dist: anthropic>=0.18.0; extra == 'llm'
Requires-Dist: google-generativeai>=0.4.0; extra == 'llm'
Requires-Dist: openai>=1.0.0; extra == 'llm'
Provides-Extra: openai
Requires-Dist: openai>=1.0.0; extra == 'openai'
